MANIFEST.in
README.rst
setup.cfg
setup.py
replmon/__init__.py
replmon/cli.py
replmon/version.py
replmon.egg-info/PKG-INFO
replmon.egg-info/SOURCES.txt
replmon.egg-info/dependency_links.txt
replmon.egg-info/entry_points.txt
replmon.egg-info/requires.txt
replmon.egg-info/top_level.txt