Metadata-Version: 1.0
Name: replmon
Version: 0.1.2
Summary: A simple MySQL replication monitor
Home-page: https://github.com/scalr-tutorials/replmon
Author: Thomas Orozco
Author-email: thomas@scalr.com
License: Apache 2.0
Platform: UNKNOWN
Classifier: Development Status :: 2 - Pre-Alpha
Classifier: Environment :: Console
Classifier: Intended Audience :: Developers
Classifier: Operating System :: OS Independent
Classifier: Programming Language :: Python :: 2
Classifier: Programming Language :: Python :: 2.6
Classifier: Programming Language :: Python :: 2.7
Classifier: License :: OSI Approved :: Apache Software License
Classifier: Topic :: System :: Systems Administration
